{
    "70010000027088": {
        "id": "0100E8C00F506000",
        "rightsId": null,
        "name": "\u65b0 \u8d85\u7ea7\u9a6c\u529b\u6b27\u5144\u5f1fU \u8c6a\u534e\u7248",
        "version": null,
        "key": null,
        "isDemo": false,
        "region": null,
        "releaseDate": 20191210,
        "nsuId": 70010000027088,
        "category": [
            "\u52a8\u4f5c",
            "\u5192\u9669",
            "\u5bb6\u5ead",
            "\u591a\u4eba"
        ],
        "ratingContent": [],
        "numberOfPlayers": 4,
        "rating": null,
        "developer": null,
        "publisher": "\u4efb\u5929\u5802",
        "frontBoxArt": null,
        "iconUrl": "https://img-eshop.cdn.nintendo.net/i/9f1dd9362cc3e14803d9f547ec90843bc510b80abe9079f9b2ec24726044d0df.jpg",
        "screenshots": [
            "https://img-eshop.cdn.nintendo.net/i/7d47efa2baba40f5518fbd1535342f3b8f383fa06d79b422d5f37c0a7fc3bb43.jpg",
            "https://img-eshop.cdn.nintendo.net/i/d5041c23ee60e6c82f024a7b93a4cd0496e7b7559a619435b746c96e0d91fd8c.jpg",
            "https://img-eshop.cdn.nintendo.net/i/8717565c2763065ec670e9a297baca77a7b7e28382e197f5f8297ca865fb1ba1.jpg",
            "https://img-eshop.cdn.nintendo.net/i/eac94b56f1490f13888a1176ca6bd402818618e771147b796aaec4214ef02c37.jpg",
            "https://img-eshop.cdn.nintendo.net/i/11204ffc9be2ebbebcaf5d84144aba741cae4f0bdb080c30a8e41dd5cacc9a69.jpg",
            "https://img-eshop.cdn.nintendo.net/i/ea9939d94ba81f834cea430ee8aa06ed7dd0d3d23b2ae42f30d9d27659483e46.jpg"
        ],
        "bannerUrl": "https://img-eshop.cdn.nintendo.net/i/1db2bdb0e20cf73e10d96cb7bfab1aea0fd2e8fed984c7950a0d582c5cf4d399.jpg",
        "intro": "2D\u8d85\u7ea7\u9a6c\u529b\u6b27\u5168\u65b0\u4f53\u9a8c\uff0c\u540c\u4eab\u6b22\u4e50\u65f6\u5149",
        "description": "\u300a\u65b0 \u8d85\u7ea7\u9a6c\u529b\u6b27\u5144\u5f1fU \u8c6a\u534e\u7248\u300b\u662f2D\u8d85\u7ea7\u9a6c\u529b\u6b27\u6a2a\u7248\u5377\u8f74\u52a8\u4f5c\u6e38\u620f\u3002\n\n\u6e38\u620f\u5305\u62ec\u300a\u65b0 \u8d85\u7ea7\u8def\u6613\u5409U\u300b\u548c\u300a\u65b0 \u8d85\u7ea7\u9a6c\u529b\u6b27\u5144\u5f1fU\u300b\u5171164\u4e2a\u5173\u5361\uff0c\u9a6c\u529b\u6b27\u4e00\u884c\u9700\u8981\u524d\u5f80\u88ab\u9177\u9738\u738b\u5360\u9886\u7684\u6843\u82b1\u516c\u4e3b\u57ce\u5821\uff0c\u5229\u7528\u591a\u79cd\u65b0\u5947\u7684\u80fd\u529b\u5f3a\u5316\uff0c\u4e0e\u53ef\u9760\u6709\u8da3\u7684\u4f19\u4f34\uff0c\u5728\u4e30\u5bcc\u591a\u5f69\u7684\u4e16\u754c\u4e2d\u5c55\u5f00\u5192\u9669\u3002\u5728\u300a\u65b0 \u8d85\u7ea7\u8def\u6613\u5409U\u300b\u4e2d\uff0c\u5173\u5361\u96be\u5ea6\u66f4\u9ad8\uff0c\u9650\u65f6\u66f4\u77ed\uff0c\u89d2\u8272\u8df3\u8dc3\u80fd\u529b\u66f4\u5f3a\u4f46\u4e5f\u66f4\u6613\u6253\u6ed1\uff0c\u975e\u5e38\u9002\u5408\u559c\u6b22\u6311\u6218\u7684\u73a9\u5bb6\u3002\n\n\u6e38\u620f\u4e2d\u6709\u201c\u9a6c\u529b\u6b27\u201d\u3001\u201c\u8def\u6613\u5409\u201d\u3001\u201c\u5947\u8bfa\u6bd4\u5965\u201d\u3001\u201c\u5077\u5929\u5154\u201d\u548c\u201c\u5947\u8bfa\u6bd4\u73c2\u201d5\u4e2a\u89d2\u8272\u4f9b\u4f60\u9009\u62e9\uff0c\u5176\u4e2d\u201c\u5947\u8bfa\u6bd4\u73c2\u201d\u4e0e\u201c\u5077\u5929\u5154\u201d\u62e5\u6709\u975e\u5e38\u9002\u5408\u65b0\u624b\u7684\u7279\u6b8a\u80fd\u529b\uff0c\u5373\u4f7f\u4e0d\u64c5\u957f\u52a8\u4f5c\u6e38\u620f\uff0c\u4e5f\u53ef\u4ee5\u8f7b\u677e\u6e38\u73a9\u3002\n\n\u9664\u4e86\u6545\u4e8b\u6a21\u5f0f\u5916\uff0c\u6e38\u620f\u8fd8\u63d0\u4f9b\u8bfe\u9898\u6a21\u5f0f\u3001\u52a0\u500d\u6a21\u5f0f\u548c\u91d1\u5e01\u5bf9\u6218\u591a\u79cd\u4e30\u5bcc\u7684\u73a9\u6cd5\u3002\u6e38\u620f\u652f\u6301\u6700\u591a4\u4eba\u4e00\u8d77\u6e38\u73a9\uff0c\u5feb\u4e0e\u4f19\u4f34\u5206\u4eabJoy-Con\u2122\uff0c\u4e00\u8d77\u8da3\u73a9\u5427\uff01",
        "languages": [
            "zh"
        ],
        "size": 2261778432
    },
    "70030000010121": {
        "id": null,
        "rightsId": null,
        "name": "\u65b0 \u8d85\u7ea7\u9a6c\u529b\u6b27\u5144\u5f1fU \u8c6a\u534e\u7248\uff08\u4f53\u9a8c\u7248\uff09",
        "version": null,
        "key": null,
        "isDemo": true,
        "region": null,
        "releaseDate": null,
        "nsuId": 70030000010121,
        "category": null,
        "ratingContent": [],
        "numberOfPlayers": null,
        "rating": null,
        "developer": null,
        "publisher": null,
        "frontBoxArt": null,
        "iconUrl": null,
        "screenshots": null,
        "bannerUrl": null,
        "intro": null,
        "description": null,
        "languages": null,
        "size": 757071872,
        "parentId": "0100E8C00F506000"
    }
}